llm_vertex.py
llm_vertex-0.2.3.dist-info/licenses/LICENSE
llm_vertex-0.2.3.dist-info/METADATA
llm_vertex-0.2.3.dist-info/WHEEL
llm_vertex-0.2.3.dist-info/entry_points.txt
llm_vertex-0.2.3.dist-info/top_level.txt
llm_vertex-0.2.3.dist-info/RECORD
