Metadata-Version: 2.4
Name: llm-vertex
Version: 0.2.3
Summary: Plugin for LLM adding support for Google Cloud Vertex AI
Author: Justyn Shull
License: Apache-2.0
Project-URL: Homepage, https://github.com/justyns/llm-vertex
Project-URL: Changelog, https://github.com/justyns/llm-vertex/releases
Project-URL: Issues, https://github.com/justyns/llm-vertex/issues
Classifier: License :: OSI Approved :: Apache Software License
Requires-Python: >3.8
License-File: LICENSE
Requires-Dist: llm
Requires-Dist: google-cloud-aiplatform>=1.81.0
Provides-Extra: dev
Requires-Dist: build>=1.2.2.post1; extra == "dev"
Requires-Dist: twine>=6.1.0; extra == "dev"
Requires-Dist: pytest>=6.0; extra == "dev"
Dynamic: license-file
